{
  "pty": {
    "component": {
      "color": {
        "tag": {
          "primary": {
            "bg": {
              "value": "{pty.semantic.color.surface.background.accent}",
              "type": "color"
            },
            "text": {
              "value": "$pty.semantic.color.text.onEmpasis.primary",
              "type": "color"
            }
          }
        },
        "footer": {
          "bg": {
            "value": "{pty.semantic.color.surface.background.primary}",
            "type": "color"
          },
          "icon": {
            "active": {
              "value": "{pty.semantic.color.icon.primary}",
              "type": "color"
            },
            "disabled": {
              "value": "{pty.semantic.color.icon.disabled}",
              "type": "color"
            }
          },
          "heading": {
            "value": "{pty.semantic.color.text.default.primary}",
            "type": "color"
          }
        },
        "detailedListItem": {
          "title": {
            "value": "{pty.semantic.color.accent.primary.background}",
            "type": "color"
          },
          "item": {
            "value": "{pty.semantic.color.text.default.primary}",
            "type": "color"
          },
          "description": {
            "value": "{pty.semantic.color.text.default.primary}",
            "type": "color"
          },
          "border": {
            "value": "{pty.semantic.color.border.default}",
            "type": "color"
          }
        },
        "header": {
          "subHeading": {
            "value": "{pty.semantic.color.text.default.primary}",
            "type": "color"
          },
          "heading": {
            "value": "{pty.semantic.color.text.default.primary}",
            "type": "color"
          },
          "icon": {
            "value": "{pty.semantic.color.accent.primary.background}",
            "type": "color"
          }
        },
        "navigation": {
          "bg": {
            "value": "{pty.semantic.color.surface.background.primary}",
            "type": "color"
          },
          "icon": {
            "active": {
              "value": "{pty.semantic.color.accent.primary.background}",
              "type": "color"
            }
          }
        },
        "snippet": {
          "forecastSnippet": {
            "time": {
              "value": "{pty.semantic.color.text.default.primary}",
              "type": "color"
            },
            "rainChance": {
              "value": "{pty.semantic.color.text.default.accent}",
              "type": "color"
            },
            "icon": {
              "value": "{pty.semantic.color.icon.primary}",
              "type": "color"
            },
            "temp": {
              "value": "{pty.semantic.color.text.default.primary}",
              "type": "color"
            }
          },
          "whatToPackSnippet": {
            "item": {
              "value": "{pty.semantic.color.text.default.primary}",
              "type": "color"
            },
            "icon": {
              "value": "{pty.semantic.color.icon.primary}",
              "type": "color"
            },
            "reason": {
              "value": "{pty.semantic.color.text.default.primary}",
              "type": "color"
            }
          }
        },
        "cardScrollable": {
          "title": {
            "value": "{pty.semantic.color.text.default.accent}",
            "type": "color"
          },
          "border": {
            "value": "{pty.semantic.color.border.default}",
            "type": "color"
          }
        },
        "app": {
          "background": {
            "value": "{pty.semantic.color.surface.background.primary}",
            "type": "color"
          }
        }
      },
      "space": {
        "tag": {
          "medium": {
            "paddingAll": {
              "value": "{pty.semantic.space.xsmall}",
              "type": "spacing"
            }
          }
        },
        "header": {
          "verticalPadding": {
            "value": "{pty.semantic.space.small}",
            "type": "spacing"
          }
        },
        "detailedListItem": {
          "horizontalSpacing": {
            "value": "{pty.semantic.space.medium}",
            "type": "spacing"
          },
          "paddingTop": {
            "value": "{pty.semantic.space.small}",
            "type": "spacing"
          },
          "paddingBottom": {
            "value": "{pty.semantic.space.medium}",
            "type": "spacing"
          },
          "verticalSpacing": {
            "value": "{pty.semantic.space.small}",
            "type": "spacing"
          }
        },
        "footer": {
          "paddingTop": {
            "value": "{pty.semantic.space.small}",
            "type": "spacing"
          },
          "paddingBottom": {
            "value": "{pty.semantic.space.large}",
            "type": "spacing"
          },
          "paddingLeftRight": {
            "value": "{pty.semantic.space.medium}",
            "type": "spacing"
          }
        },
        "navigation": {
          "paddingTop": {
            "value": "{pty.semantic.space.xxlarge}",
            "type": "spacing"
          },
          "paddingBottom": {
            "value": "{pty.semantic.space.small}",
            "type": "spacing"
          },
          "paddingLeftRight": {
            "value": "{pty.semantic.space.medium}",
            "type": "spacing"
          }
        },
        "cardScrollable": {
          "paddingTop": {
            "value": "{pty.semantic.space.small}",
            "type": "spacing"
          },
          "paddingBottom": {
            "value": "{pty.semantic.space.medium}",
            "type": "spacing"
          },
          "verticalSpacing": {
            "value": "{pty.semantic.space.small}",
            "type": "spacing"
          },
          "horizontalSpacing": {
            "value": "{pty.semantic.space.xsmall}",
            "type": "spacing"
          }
        },
        "wrapper": {
          "paddingLeftRight": {
            "value": "{pty.semantic.space.medium}",
            "type": "spacing"
          },
          "paddingBottom": {
            "value": "{pty.semantic.space.large}",
            "type": "spacing"
          },
          "paddingTop": {
            "value": "{pty.semantic.space.xlarge}",
            "type": "spacing"
          },
          "verticalSpacing": {
            "value": "{pty.semantic.space.xlarge}",
            "type": "spacing"
          }
        }
      },
      "size": {
        "header": {
          "icon": {
            "value": "{pty.semantic.size.small}",
            "type": "sizing"
          }
        },
        "snippet": {
          "forecastSnippet": {
            "height": {
              "value": "{pty.semantic.size.xlarge}",
              "type": "sizing"
            },
            "width": {
              "value": "{pty.semantic.size.medium}",
              "type": "sizing"
            }
          },
          "whatToPackSnippet": {
            "height": {
              "value": "{pty.semantic.size.xlarge}",
              "type": "sizing"
            },
            "width": {
              "value": "{pty.semantic.size.large}",
              "type": "sizing"
            },
            "icon": {
              "value": "{pty.semantic.size.medium}",
              "type": "sizing"
            }
          }
        },
        "footer": {
          "icon": {
            "value": "{pty.semantic.size.small}",
            "type": "sizing"
          }
        }
      },
      "type": {
        "detailedListItem": {
          "title": {
            "value": "{pty.semantic.type.headline.medium}",
            "type": "typography"
          },
          "item": {
            "value": "{pty.semantic.type.title.large}",
            "type": "typography"
          },
          "description": {
            "value": "{pty.semantic.type.body.medium}",
            "type": "typography"
          }
        },
        "header": {
          "title": {
            "value": "{pty.semantic.type.display.large}",
            "type": "typography"
          },
          "subHeading": {
            "value": "{pty.semantic.type.body.medium}",
            "type": "typography"
          }
        },
        "footer": {
          "heading": {
            "value": "{pty.semantic.type.title.medium}",
            "type": "typography"
          }
        },
        "snippet": {
          "forecastSnippet": {
            "time": {
              "value": "{pty.semantic.type.headline.small}",
              "type": "typography"
            },
            "rainChance": {
              "value": "{pty.semantic.type.headline.small}",
              "type": "typography"
            },
            "temp": {
              "value": "{pty.semantic.type.title.small}",
              "type": "typography"
            }
          },
          "whatToPackSnippet": {
            "item": {
              "value": "{pty.semantic.type.headline.small}",
              "type": "typography"
            },
            "reason": {
              "value": "{pty.semantic.type.title.small}",
              "type": "typography"
            }
          },
          "forecast": {
            "title": {
              "value": "{pty.semantic.type.headline.medium}",
              "type": "typography"
            }
          }
        },
        "cardScrollable": {
          "title": {
            "value": "{pty.semantic.type.headline.medium}",
            "type": "typography"
          }
        },
        "tag": {
          "medium": {
            "value": "{pty.semantic.type.label.small}",
            "type": "typography"
          }
        },
        "navigation": {
          "heading": {
            "value": "{pty.semantic.type.title.medium}",
            "type": "typography"
          }
        }
      },
      "radius": {
        "tag": {
          "medium": {
            "value": "{pty.semantic.radius.default}",
            "type": "borderRadius"
          }
        }
      }
    }
  }
}